[
  {
    "id": "G5vYZ_dhIRmV4",
    "ids": [
      "G5vYZ_dhIRmV4"
    ],
    "name": "The Fray-summer Of Light Tour With Dashboard Confessional",
    "primary_artist": "The Fray",
    "venue_name": "Greek Theatre-U.C. Berkeley",
    "city": "Berkeley",
    "state": "CA",
    "country": "US",
    "url": "https://www.ticketmaster.com/the-fraysummer-of-light-tour-with-berkeley-california-07-23-2026/event/1C006436E8BEED15",
    "window": "short_term",
    "local_date": "2026-07-23",
    "start_datetime": "2026-07-24T01:00:00+00:00",
    "date_start": "2026-07-24T01:00:00+00:00",
    "date_end": "2026-07-24T01:00:00+00:00",
    "multi_night": false,
    "night_count": 1,
    "score": 0.7029999999999998,
    "ai_priority": 8,
    "ai_reason": "The Fray and Dashboard Confessional evoke nostalgia while still appealing to a new generation, making this a compelling show."
  },
  {
    "id": "G5vYZbMxHi14A",
    "ids": [
      "G5vYZbMxHi14A"
    ],
    "name": "Evanescence 2026 World Tour with Spiritbox and Nova Twins",
    "primary_artist": "Evanescence",
    "venue_name": "Shoreline Amphitheatre",
    "city": "Mountain View",
    "state": "CA",
    "country": "US",
    "url": "https://www.ticketmaster.com/evanescence-2026-world-tour-with-spiritbox-mountain-view-california-07-20-2026/event/1C006378BCB0A545",
    "window": "short_term",
    "local_date": "2026-07-20",
    "start_datetime": "2026-07-21T02:00:00+00:00",
    "date_start": "2026-07-21T02:00:00+00:00",
    "date_end": "2026-07-21T02:00:00+00:00",
    "multi_night": false,
    "night_count": 1,
    "score": 0.7029999999999998,
    "ai_priority": 8,
    "ai_reason": "Evanescence's reputation for dramatic and powerful performances makes this tour a significant event for rock fans."
  },
  {
    "id": "G5vYZ_F-Fb7tp",
    "ids": [
      "G5vYZ_F-Fb7tp"
    ],
    "name": "RETRO JUNKIE Summer Fest 2026",
    "primary_artist": "George Michael Reborn - A Tribute to George Michael",
    "venue_name": "Toyota Pavilion at Concord",
    "city": "Concord",
    "state": "CA",
    "country": "US",
    "url": "https://www.ticketmaster.com/retro-junkie-summer-fest-2026-concord-california-07-25-2026/event/1C00648848604A56",
    "window": "short_term",
    "local_date": "2026-07-25",
    "start_datetime": "2026-07-25T21:00:00+00:00",
    "date_start": "2026-07-25T21:00:00+00:00",
    "date_end": "2026-07-25T21:00:00+00:00",
    "multi_night": false,
    "night_count": 1,
    "score": 0.694,
    "ai_priority": 8,
    "ai_reason": "Jimmy Eat World's 25th anniversary of 'Bleed American' is a nostalgic celebration that resonates with long-time fans."
  },
  {
    "id": "Z7r9jZ1A7xfZ-",
    "ids": [
      "Z7r9jZ1A7xfZ-",
      "Z7r9jZ1A7xfZx"
    ],
    "name": "ENHYPEN",
    "primary_artist": "ENHYPEN",
    "venue_name": "Oakland Arena",
    "city": "Oakland",
    "state": "CA",
    "country": "US",
    "url": "https://www.ticketmaster.com/event/Z7r9jZ1A7xfZ-",
    "window": "short_term",
    "local_date": "2026-07-28",
    "start_datetime": "2026-07-29T02:30:00+00:00",
    "date_start": "2026-07-29T02:30:00+00:00",
    "date_end": "2026-07-30T02:30:00+00:00",
    "multi_night": true,
    "night_count": 2,
    "score": 0.7089999999999999,
    "ai_priority": 7,
    "ai_reason": "ENHYPEN's popularity in the K-pop scene makes their shows highly anticipated events, attracting a diverse audience."
  },
  {
    "id": "G5vYZ_1B5_QnH",
    "ids": [
      "G5vYZ_1B5_QnH"
    ],
    "name": "2026 WOODZ WORLD TOUR ' Archive. 1 ' IN US",
    "primary_artist": "WOODZ",
    "venue_name": "San Jose Civic",
    "city": "San Jose",
    "state": "CA",
    "country": "US",
    "url": "https://www.ticketmaster.com/2026-woodz-world-tour-archive-1-san-jose-california-07-27-2026/event/1C0064AE8B65AABC",
    "window": "short_term",
    "local_date": "2026-07-27",
    "start_datetime": "2026-07-28T02:30:00+00:00",
    "date_start": "2026-07-28T02:30:00+00:00",
    "date_end": "2026-07-28T02:30:00+00:00",
    "multi_night": false,
    "night_count": 1,
    "score": 0.691,
    "ai_priority": 7,
    "ai_reason": "WOODZ's world tour showcases a rising K-pop star, tapping into the growing interest in global pop phenomena."
  },
  {
    "id": "G5vYZ_6LIFmOe",
    "ids": [
      "G5vYZ_6LIFmOe"
    ],
    "name": "Benson Boone: Wanted Man Tour",
    "primary_artist": "Benson Boone",
    "venue_name": "SAP Center at San Jose",
    "city": "San Jose",
    "state": "CA",
    "country": "US",
    "url": "https://www.ticketmaster.com/benson-boone-wanted-man-tour-san-jose-california-08-07-2026/event/1C006477E822E802",
    "window": "short_term",
    "local_date": "2026-08-07",
    "start_datetime": "2026-08-08T03:00:00+00:00",
    "date_start": "2026-08-08T03:00:00+00:00",
    "date_end": "2026-08-08T03:00:00+00:00",
    "multi_night": false,
    "night_count": 1,
    "score": 0.6759999999999999,
    "ai_priority": 7,
    "ai_reason": "Benson Boone's emerging talent and strong online presence make his tour a noteworthy event for pop music fans."
  },
  {
    "id": "G5vYZ_dK3rqfU",
    "ids": [
      "G5vYZ_dK3rqfU"
    ],
    "name": "Tedeschi Trucks Band",
    "primary_artist": "Tedeschi Trucks Band",
    "venue_name": "Greek Theatre-U.C. Berkeley",
    "city": "Berkeley",
    "state": "CA",
    "country": "US",
    "url": "https://www.ticketmaster.com/tedeschi-trucks-band-berkeley-california-08-12-2026/event/1C006434D279D536",
    "window": "short_term",
    "local_date": "2026-08-12",
    "start_datetime": "2026-08-13T01:00:00+00:00",
    "date_start": "2026-08-13T01:00:00+00:00",
    "date_end": "2026-08-13T01:00:00+00:00",
    "multi_night": false,
    "night_count": 1,
    "score": 0.6729999999999999,
    "ai_priority": 7,
    "ai_reason": "Tedeschi Trucks Band's blend of blues and rock is known for its high-energy performances, appealing to a wide audience."
  },
  {
    "id": "G5vYZ_k3LHG-Q",
    "ids": [
      "G5vYZ_k3LHG-Q"
    ],
    "name": "Passion Pit - The Pretty Penny Tour",
    "primary_artist": "Passion Pit",
    "venue_name": "Fox Theater - Oakland",
    "city": "Oakland",
    "state": "CA",
    "country": "US",
    "url": "https://www.ticketmaster.com/passion-pit-the-pretty-penny-tour-oakland-california-08-16-2026/event/1C0064649FF0C85A",
    "window": "short_term",
    "local_date": "2026-08-16",
    "start_datetime": "2026-08-17T02:30:00+00:00",
    "date_start": "2026-08-17T02:30:00+00:00",
    "date_end": "2026-08-17T02:30:00+00:00",
    "multi_night": false,
    "night_count": 1,
    "score": 0.664,
    "ai_priority": 7,
    "ai_reason": "Passion Pit's return with a new tour promises to deliver their signature synth-pop sound to eager fans."
  },
  {
    "id": "G5vYZbU3DGDUo",
    "ids": [
      "G5vYZbU3DGDUo"
    ],
    "name": "TRAIN - Drops of Jupiter: 25 Years in the Atmosphere",
    "primary_artist": "Train",
    "venue_name": "Shoreline Amphitheatre",
    "city": "Mountain View",
    "state": "CA",
    "country": "US",
    "url": "https://www.ticketmaster.com/train-drops-of-jupiter-25-years-mountain-view-california-08-26-2026/event/1C006364BB33BD91",
    "window": "short_term",
    "local_date": "2026-08-26",
    "start_datetime": "2026-08-27T01:45:00+00:00",
    "date_start": "2026-08-27T01:45:00+00:00",
    "date_end": "2026-08-27T01:45:00+00:00",
    "multi_night": false,
    "night_count": 1,
    "score": 0.6729999999999999,
    "ai_priority": 6,
    "ai_reason": "TRAIN's anniversary tour celebrates their classic hits, appealing to fans of nostalgic rock music."
  },
  {
    "id": "G5vYZ_1xngV7n",
    "ids": [
      "G5vYZ_1xngV7n"
    ],
    "name": "Thievery Corporation",
    "primary_artist": "Thievery Corporation",
    "venue_name": "Fox Theater - Oakland",
    "city": "Oakland",
    "state": "CA",
    "country": "US",
    "url": "https://www.ticketmaster.com/thievery-corporation-oakland-california-09-12-2026/event/1C0064A8AAD7412A",
    "window": "short_term",
    "local_date": "2026-09-12",
    "start_datetime": "2026-09-13T03:00:00+00:00",
    "date_start": "2026-09-13T03:00:00+00:00",
    "date_end": "2026-09-13T03:00:00+00:00",
    "multi_night": false,
    "night_count": 1,
    "score": 0.664,
    "ai_priority": 6,
    "ai_reason": "Courtney Barnett's distinctive voice and storytelling style make her shows a captivating experience for indie rock lovers."
  },
  {
    "id": "G5vYZ_aKcpNsg",
    "ids": [
      "G5vYZ_aKcpNsg"
    ],
    "name": "Peter Noone",
    "primary_artist": "Peter Noone",
    "venue_name": "Uptown Theatre Napa",
    "city": "Napa",
    "state": "CA",
    "country": "US",
    "url": "https://www.ticketmaster.com/peter-noone-napa-california-08-07-2026/event/1C006494ED5A3C75",
    "window": "short_term",
    "local_date": "2026-08-07",
    "start_datetime": "2026-08-08T03:00:00+00:00",
    "date_start": "2026-08-08T03:00:00+00:00",
    "date_end": "2026-08-08T03:00:00+00:00",
    "multi_night": false,
    "night_count": 1,
    "score": 0.643,
    "ai_priority": 6,
    "ai_reason": "Lil Wayne's 20-year celebration of 'The Carter' series is sure to attract hip-hop fans eager for a nostalgic experience."
  },
  {
    "id": "G5vYZ_AK8hrHj",
    "ids": [
      "G5vYZ_AK8hrHj"
    ],
    "name": "Low Cut Connie",
    "primary_artist": "Low Cut Connie",
    "venue_name": "The Fillmore",
    "city": "San Francisco",
    "state": "CA",
    "country": "US",
    "url": "https://www.ticketmaster.com/low-cut-connie-san-francisco-california-07-15-2026/event/1C006454D06DEF1C",
    "window": "short_term",
    "local_date": "2026-07-15",
    "start_datetime": "2026-07-16T03:00:00+00:00",
    "date_start": "2026-07-16T03:00:00+00:00",
    "date_end": "2026-07-16T03:00:00+00:00",
    "multi_night": false,
    "night_count": 1,
    "score": 0.694,
    "ai_priority": null,
    "ai_reason": null
  }
]